albatross_extras/__init__.py
albatross_extras/handler/__init__.py
albatross_extras/handler/file.py
albatross_extras/handler/health.py
albatross_extras/handler/template.py
albatross_extras/lib/__init__.py
albatross_extras/lib/config.py
albatross_extras/lib/logging.py
albatross_extras/lib/stats.py
albatross_extras/lib/util.py
albatross_extras/middleware/__init__.py
albatross_extras/middleware/auth.py
albatross_extras/middleware/cors.py
albatross_extras/middleware/logging.py
albatross_extras/middleware/statsd.py
albatross_extras-0.2.0.dist-info/DESCRIPTION.rst
albatross_extras-0.2.0.dist-info/METADATA
albatross_extras-0.2.0.dist-info/RECORD
albatross_extras-0.2.0.dist-info/WHEEL
albatross_extras-0.2.0.dist-info/metadata.json
albatross_extras-0.2.0.dist-info/top_level.txt
tests/handler/__init__.py
tests/handler/test_file.py
tests/handler/test_health.py
tests/handler/test_template.py
tests/lib/__init__.py
tests/lib/test_config.py
tests/lib/test_logging.py
tests/lib/test_util.py
tests/middleware/__init__.py
tests/middleware/test_auth.py
tests/middleware/test_logging.py
tests/middleware/test_statsd.py
