Metadata-Version: 2.0
Name: albatross-extras
Version: 0.2.0
Summary: Utilities for albatross web framework
Home-page: https://github.com/kespindler/albatross_extras
Author: Kurt Spindler
Author-email: kespindler@gmail.com
License: MIT
Keywords: web http server async
Platform: UNKNOWN
Classifier: Development Status :: 3 - Alpha
Classifier: Intended Audience :: Developers
Classifier: License :: OSI Approved :: MIT License
Classifier: Programming Language :: Python :: 3.5
Provides-Extra: ujson
Requires-Dist: ujson; extra == 'ujson'
